paquete1/__init__.py
paquete1/course.py
paquete1/utils.py
paquete1-0.1.0.dist-info/METADATA
paquete1-0.1.0.dist-info/WHEEL
paquete1-0.1.0.dist-info/top_level.txt
paquete1-0.1.0.dist-info/RECORD
