Metadata-Version: 2.4
Name: paquete1
Version: 0.1.0
Summary: Una biblioteca para consultar cursos de hack4u
Home-page: https://hack4u.io
Author: Eric Villarreal
Dynamic: author
Dynamic: description
Dynamic: description-content-type
Dynamic: home-page
Dynamic: summary
